demo/__init__.py
demo/app.py
demo/utils.py
ragvizexpander/__init__.py
ragvizexpander/constants.py
ragvizexpander/projections.py
ragvizexpander/query_expansion.py
ragvizexpander/rag.py
ragvizexpander/ragvizchain.py
ragvizexpander/embeddings/__init__.py
ragvizexpander/embeddings/hf_based.py
ragvizexpander/embeddings/ollama_based.py
ragvizexpander/embeddings/openai.py
ragvizexpander/embeddings/st_based.py
ragvizexpander/embeddings/tei_based.py
ragvizexpander/llms/__init__.py
ragvizexpander/llms/llamacpp_based.py
ragvizexpander/llms/ollama_based.py
ragvizexpander/llms/openai_based.py
ragvizexpander/loaders/__init__.py
ragvizexpander/loaders/docx_loader.py
ragvizexpander/loaders/pdf_loader.py
ragvizexpander/loaders/pptx_loader.py
ragvizexpander/loaders/txt_loader.py
ragvizexpander/splitters/__init__.py
ragvizexpander/splitters/char_splitter.py
ragvizexpander/splitters/recursive_char2token_splitter.py
ragvizexpander/splitters/token_splitter.py
ragvizexpander-1.1.0.dist-info/LICENSE
ragvizexpander-1.1.0.dist-info/METADATA
ragvizexpander-1.1.0.dist-info/WHEEL
ragvizexpander-1.1.0.dist-info/top_level.txt
ragvizexpander-1.1.0.dist-info/RECORD
