Metadata-Version: 2.1
Name: ragvizexpander
Version: 1.1.0
Summary: A open-source tool to to visualise your RAG documents 🔮.
Home-page: https://github.com/KKenny0/RAGVizExpander.git
Author: Kenny Wu
Author-email: jdlow@live.cn
Classifier: Programming Language :: Python :: 3
Classifier: License :: OSI Approved :: MIT License
Classifier: Operating System :: OS Independent
Requires-Python: >=3.10
License-File: LICENSE
Requires-Dist: numpy
Requires-Dist: pandas
Requires-Dist: umap-learn
Requires-Dist: sentence-transformers
Requires-Dist: plotly
Requires-Dist: tqdm
Requires-Dist: PyPDF2
Requires-Dist: langchain
Requires-Dist: chromadb
Requires-Dist: openai
Requires-Dist: pydantic
Requires-Dist: json-repair
Requires-Dist: ollama
Requires-Dist: python-docx
Requires-Dist: python-pptx
